__init__.py
qcontext/__init__.py
qcontext/contextapi.py
qcontext/qasyncio.py
qcontext/.assets/activity.svg
qcontext/.assets/airplay.svg
qcontext/.assets/alert-circle.svg
qcontext/.assets/alert-octagon.svg
qcontext/.assets/alert-triangle.svg
qcontext/.assets/align-center.svg
qcontext/.assets/align-justify.svg
qcontext/.assets/align-left.svg
qcontext/.assets/align-right.svg
qcontext/.assets/anchor.svg
qcontext/.assets/aperture.svg
qcontext/.assets/archive.svg
qcontext/.assets/arrow-down-circle.svg
qcontext/.assets/arrow-down-left.svg
qcontext/.assets/arrow-down-right.svg
qcontext/.assets/arrow-down.svg
qcontext/.assets/arrow-left-circle.svg
qcontext/.assets/arrow-left.svg
qcontext/.assets/arrow-right-circle.svg
qcontext/.assets/arrow-right.svg
qcontext/.assets/arrow-up-circle.svg
qcontext/.assets/arrow-up-left.svg
qcontext/.assets/arrow-up-right.svg
qcontext/.assets/arrow-up.svg
qcontext/.assets/at-sign.svg
qcontext/.assets/award.svg
qcontext/.assets/bar-chart-2.svg
qcontext/.assets/bar-chart.svg
qcontext/.assets/battery-charging.svg
qcontext/.assets/battery.svg
qcontext/.assets/bell-off.svg
qcontext/.assets/bell.svg
qcontext/.assets/bluetooth.svg
qcontext/.assets/bold.svg
qcontext/.assets/book-open.svg
qcontext/.assets/book.svg
qcontext/.assets/bookmark.svg
qcontext/.assets/box.svg
qcontext/.assets/briefcase.svg
qcontext/.assets/calendar.svg
qcontext/.assets/camera-off.svg
qcontext/.assets/camera.svg
qcontext/.assets/cast.svg
qcontext/.assets/check-circle.svg
qcontext/.assets/check-square.svg
qcontext/.assets/check.svg
qcontext/.assets/chevron-down.svg
qcontext/.assets/chevron-left.svg
qcontext/.assets/chevron-right.svg
qcontext/.assets/chevron-up.svg
qcontext/.assets/chevrons-down.svg
qcontext/.assets/chevrons-left.svg
qcontext/.assets/chevrons-right.svg
qcontext/.assets/chevrons-up.svg
qcontext/.assets/chrome.svg
qcontext/.assets/circle.svg
qcontext/.assets/clipboard.svg
qcontext/.assets/clock.svg
qcontext/.assets/cloud-drizzle.svg
qcontext-1.0.7.dist-info/LICENSE.txt
qcontext-1.0.7.dist-info/METADATA
qcontext-1.0.7.dist-info/WHEEL
qcontext-1.0.7.dist-info/top_level.txt
qcontext-1.0.7.dist-info/RECORD
