Metadata-Version: 2.1
Name: qcontext
Version: 1.0.7
Summary: One of the most controversial things
Author-email: cxllmerichie <cxllmerichie@gmail.com>
Maintainer-email: cxllmerichie <cxllmerichie@gmail.com>
License: MIT License
Project-URL: Homepage, https://github.com/cxllmerichie/qcontext
Project-URL: Bug Tracker, https://github.com/cxllmerichie/qcontext/issues
Project-URL: Repository, https://github.com/cxllmerichie/qcontext
Project-URL: Documentation, https://github.com/cxllmerichie/qcontext/README.md
Classifier: Topic :: Software Development :: Libraries :: Python Modules
Classifier: Programming Language :: Python :: Implementation :: CPython
Classifier: Programming Language :: Python :: 3.10
Classifier: Natural Language :: English
Classifier: Intended Audience :: Developers
Classifier: Operating System :: OS Independent
Classifier: License :: OSI Approved :: MIT License
Requires-Python: >=3.10
License-File: LICENSE.txt
Requires-Dist: PyQt5 (~=5.15.9)
Requires-Dist: PyQt5-stubs (~=5.15.6.0)
Requires-Dist: qasync (~=0.24.0)
Requires-Dist: loguru (~=0.6.0)
